langextract/__init__.py
langextract/annotation.py
langextract/chunking.py
langextract/data.py
langextract/data_lib.py
langextract/exceptions.py
langextract/extraction.py
langextract/factory.py
langextract/inference.py
langextract/plugins.py
langextract/prompt_validation.py
langextract/prompting.py
langextract/py.typed
langextract/registry.py
langextract/resolver.py
langextract/schema.py
langextract/tokenizer.py
langextract/_compat/README.md
langextract/_compat/__init__.py
langextract/_compat/exceptions.py
langextract/_compat/inference.py
langextract/_compat/registry.py
langextract/_compat/schema.py
langextract/core/__init__.py
langextract/core/base_model.py
langextract/core/data.py
langextract/core/debug_utils.py
langextract/core/exceptions.py
langextract/core/format_handler.py
langextract/core/schema.py
langextract/core/tokenizer.py
langextract/core/types.py
langextract/providers/README.md
langextract/providers/__init__.py
langextract/providers/builtin_registry.py
langextract/providers/patterns.py
langextract/providers/router.py
langextract/providers/schemas/__init__.py
bioscope_langextract-0.0.1.dist-info/METADATA
bioscope_langextract-0.0.1.dist-info/WHEEL
bioscope_langextract-0.0.1.dist-info/licenses/LICENSE
bioscope_langextract-0.0.1.dist-info/RECORD
