Metadata-Version: 2.4
Name: bioscope-langextract
Version: 0.0.1
Summary: A lightweight library for extracting structured data from language models
Project-URL: Homepage, https://github.com/bioscope-ai/bioscope-langextract
Project-URL: Repository, https://github.com/bioscope-ai/bioscope-langextract
Project-URL: Bug Tracker, https://github.com/bioscope-ai/bioscope-langextract/issues
Author-email: Bioscope <development@bioscope.ai>
License-Expression: Apache-2.0
License-File: LICENSE
Requires-Python: >=3.13
Requires-Dist: exceptiongroup>=1.1.0
Requires-Dist: more-itertools>=8.0.0
Requires-Dist: pydantic>=2.0.0
Requires-Dist: python-dotenv>=0.19.0
Requires-Dist: pyyaml>=6.0
Requires-Dist: regex>=2023.0.0
Requires-Dist: typing-extensions>=4.0.0
Provides-Extra: dev
Requires-Dist: isort>=5.13.0; extra == 'dev'
Requires-Dist: pyink~=24.3.0; extra == 'dev'
Requires-Dist: pytest>=7.4.0; extra == 'dev'
